chaussette/__init__.py
chaussette/_paste.py
chaussette/server.py
chaussette/util.py
chaussette/backend/__init__.py
chaussette/backend/_bjoern.py
chaussette/backend/_eventlet.py
chaussette/backend/_fastgevent.py
chaussette/backend/_gevent.py
chaussette/backend/_geventwebsocket.py
chaussette/backend/_geventws4py.py
chaussette/backend/_meinheld.py
chaussette/backend/_socketio.py
chaussette/backend/_tornado.py
chaussette/backend/_waitress.py
chaussette/backend/_wsgiref.py
chaussette/tests/__init__.py
chaussette/tests/support.py
chaussette/tests/test_backend.py
chaussette/tests/test_paste.py
chaussette/tests/test_server.py
chaussette/tests/test_util.py
chaussette_backport-1.3.1.dist-info/LICENSE
chaussette_backport-1.3.1.dist-info/METADATA
chaussette_backport-1.3.1.dist-info/WHEEL
chaussette_backport-1.3.1.dist-info/entry_points.txt
chaussette_backport-1.3.1.dist-info/top_level.txt
chaussette_backport-1.3.1.dist-info/RECORD
