Metadata-Version: 2.1
Name: chaussette-backport
Version: 1.3.1
Summary: A WSGI Server for Circus
Home-page: https://chaussette.readthedocs.io
Author: Mozilla Foundation & Contributors
Author-email: services-dev@lists.mozila.org
Classifier: Programming Language :: Python
Classifier: Programming Language :: Python :: 2
Classifier: Programming Language :: Python :: 2.6
Classifier: Programming Language :: Python :: 2.7
Classifier: Programming Language :: Python :: 3
Classifier: Programming Language :: Python :: 3.3
Classifier: Programming Language :: Python :: 3.4
Classifier: License :: OSI Approved :: Apache Software License
Classifier: Development Status :: 3 - Alpha
License-File: LICENSE
Requires-Dist: six (>=1.3.0)
